altsportsleagues/__init__.py
altsportsleagues/client.py
altsportsleagues/exceptions.py
altsportsleagues/models.py
altsportsleagues-1.0.0.dist-info/licenses/LICENSE
altsportsleagues-1.0.0.dist-info/METADATA
altsportsleagues-1.0.0.dist-info/WHEEL
altsportsleagues-1.0.0.dist-info/top_level.txt
altsportsleagues-1.0.0.dist-info/RECORD
