Metadata-Version: 2.4
Name: altsportsleagues
Version: 1.0.0
Summary: Python SDK for AltSportsLeagues platform - enabling league owners to get compliant and onboarded with sportsbooks
Home-page: https://github.com/altsportsleagues/altsportsleagues-python
Author: AltSportsLeagues.ai
Author-email: "AltSportsLeagues.ai" <dev@altsportsleagues.ai>
License: MIT
Project-URL: Homepage, https://altsportsleagues.ai
Project-URL: Documentation, https://docs.altsportsleagues.ai
Project-URL: Repository, https://github.com/ai-assistant-altsportsdata/altsportsleagues-python
Project-URL: Issues, https://github.com/ai-assistant-altsportsdata/altsportsleagues-python/issues
Project-URL: Changelog, https://github.com/ai-assistant-altsportsdata/altsportsleagues-python/blob/main/CHANGELOG.md
Keywords: sports,leagues,betting,compliance,sportsbook,api,sdk
Classifier: Development Status :: 4 - Beta
Classifier: Intended Audience :: Developers
Classifier: License :: OSI Approved :: MIT License
Classifier: Programming Language :: Python :: 3
Classifier: Programming Language :: Python :: 3.8
Classifier: Programming Language :: Python :: 3.9
Classifier: Programming Language :: Python :: 3.10
Classifier: Programming Language :: Python :: 3.11
Classifier: Programming Language :: Python :: 3.12
Classifier: Topic :: Software Development :: Libraries :: Python Modules
Classifier: Topic :: Internet :: WWW/HTTP
Classifier: Topic :: Games/Entertainment :: Board Games
Requires-Python: >=3.8
License-File: LICENSE
Requires-Dist: requests>=2.28.0
Requires-Dist: pydantic>=2.0.0
Requires-Dist: python-dateutil>=2.8.0
Provides-Extra: dev
Requires-Dist: pytest>=7.0.0; extra == "dev"
Requires-Dist: pytest-cov>=4.0.0; extra == "dev"
Requires-Dist: black>=22.0.0; extra == "dev"
Requires-Dist: isort>=5.10.0; extra == "dev"
Requires-Dist: mypy>=1.0.0; extra == "dev"
Requires-Dist: sphinx>=5.0.0; extra == "dev"
Requires-Dist: sphinx-rtd-theme>=1.2.0; extra == "dev"
Provides-Extra: docs
Requires-Dist: sphinx>=5.0.0; extra == "docs"
Requires-Dist: sphinx-rtd-theme>=1.2.0; extra == "docs"
Dynamic: author
Dynamic: home-page
Dynamic: license-file
Dynamic: requires-python
